{
  "positions": [
    {
      "address": "0xb7b7eb7e9611975bc9715f22ce7e6ee288296fd4",
      "healthFactor": 1.1648,
      "collateralValue": 14069223.48,
      "borrowValue": 9786205.42,
      "liquidationThreshold": 0.8101,
      "collateralAsset": "Mixed",
      "borrowAsset": "Mixed",
      "collateralAmount": 1
    }
  ],
  "meta": {
    "chain": "ethereum",
    "timestamp": "2026-02-07T09:00:56.940631",
    "filters": {
      "maxHealthFactor": 2,
      "minCollateralUsd": 100000
    },
    "totalPositions": 1,
    "totalCollateralUsd": 14069223.48,
    "totalBorrowUsd": 9786205.42
  }
}